odoo10_addon_keychain-10.0.2.0.2-py3.6-nspkg.pth
odoo/addons/keychain/README.rst
odoo/addons/keychain/__init__.py
odoo/addons/keychain/__manifest__.py
odoo/addons/keychain/i18n/am.po
odoo/addons/keychain/i18n/ar.po
odoo/addons/keychain/i18n/bg.po
odoo/addons/keychain/i18n/bs.po
odoo/addons/keychain/i18n/ca.po
odoo/addons/keychain/i18n/ca_ES.po
odoo/addons/keychain/i18n/cs.po
odoo/addons/keychain/i18n/da.po
odoo/addons/keychain/i18n/de.po
odoo/addons/keychain/i18n/el_GR.po
odoo/addons/keychain/i18n/en_GB.po
odoo/addons/keychain/i18n/es.po
odoo/addons/keychain/i18n/es_AR.po
odoo/addons/keychain/i18n/es_CL.po
odoo/addons/keychain/i18n/es_CO.po
odoo/addons/keychain/i18n/es_CR.po
odoo/addons/keychain/i18n/es_DO.po
odoo/addons/keychain/i18n/es_EC.po
odoo/addons/keychain/i18n/es_ES.po
odoo/addons/keychain/i18n/es_MX.po
odoo/addons/keychain/i18n/es_PE.po
odoo/addons/keychain/i18n/es_PY.po
odoo/addons/keychain/i18n/es_VE.po
odoo/addons/keychain/i18n/et.po
odoo/addons/keychain/i18n/eu.po
odoo/addons/keychain/i18n/fa.po
odoo/addons/keychain/i18n/fi.po
odoo/addons/keychain/i18n/fr.po
odoo/addons/keychain/i18n/fr_CA.po
odoo/addons/keychain/i18n/fr_CH.po
odoo/addons/keychain/i18n/gl.po
odoo/addons/keychain/i18n/gl_ES.po
odoo/addons/keychain/i18n/he.po
odoo/addons/keychain/i18n/hr.po
odoo/addons/keychain/i18n/hr_HR.po
odoo/addons/keychain/i18n/hu.po
odoo/addons/keychain/i18n/id.po
odoo/addons/keychain/i18n/it.po
odoo/addons/keychain/i18n/ja.po
odoo/addons/keychain/i18n/keychain.pot
odoo/addons/keychain/i18n/ko.po
odoo/addons/keychain/i18n/lt.po
odoo/addons/keychain/i18n/lt_LT.po
odoo/addons/keychain/i18n/lv.po
odoo/addons/keychain/i18n/mk.po
odoo/addons/keychain/i18n/mn.po
odoo/addons/keychain/i18n/nb.po
odoo/addons/keychain/i18n/nb_NO.po
odoo/addons/keychain/i18n/nl.po
odoo/addons/keychain/i18n/nl_BE.po
odoo/addons/keychain/i18n/nl_NL.po
odoo/addons/keychain/i18n/pl.po
odoo/addons/keychain/i18n/pt.po
odoo/addons/keychain/i18n/pt_BR.po
odoo/addons/keychain/i18n/pt_PT.po
odoo10_addon_keychain-10.0.2.0.2.dist-info/METADATA
odoo10_addon_keychain-10.0.2.0.2.dist-info/WHEEL
odoo10_addon_keychain-10.0.2.0.2.dist-info/namespace_packages.txt
odoo10_addon_keychain-10.0.2.0.2.dist-info/top_level.txt
odoo10_addon_keychain-10.0.2.0.2.dist-info/RECORD
