Metadata-Version: 2.1
Name: odoo10-addon-keychain
Version: 10.0.2.0.2
Summary: Store accounts and credentials
Home-page: https://akretion.com/
Author: Akretion, Odoo Community Association (OCA)
Author-email: support@odoo-community.org
License: AGPL-3
Platform: UNKNOWN
Classifier: Programming Language :: Python
Classifier: Framework :: Odoo
Classifier: License :: OSI Approved :: GNU Affero General Public License v3
Requires-Python: ~=2.7
Requires-Dist: cryptography
Requires-Dist: odoo (<10.1dev,>=10.0)
